ringneck/__init__.py
ringneck/error_handler.py
ringneck/grammar.md
ringneck/interpreter.py
ringneck/parser.py
ringneck/py.typed
ringneck/scanner.py
ringneck/tokens.py
ringneck/ast/__init__.py
ringneck/ast/base.py
ringneck/ast/expression.py
ringneck/ast/printer.py
ringneck/ast/statement.py
ringneck/tests/__init__.py
ringneck/tests/cases.py
ringneck/tests/test_embedded.py
ringneck/tests/test_interpreter.py
ringneck/tests/test_parser.py
ringneck/tests/test_scanner.py
ringneck-0.0.5.dist-info/METADATA
ringneck-0.0.5.dist-info/WHEEL
ringneck-0.0.5.dist-info/entry_points.txt
ringneck-0.0.5.dist-info/licenses/LICENSE
ringneck-0.0.5.dist-info/RECORD
