Metadata-Version: 2.1
Name: ringneck
Version: 0.0.5
Summary: A Python-ish script interpreter.
Project-URL: Homepage, https://github.com/gregersn/ringneck
Author-email: Greger Stolt Nilsen <gregersn@gmail.com>
License: MIT License
License-File: LICENSE
Keywords: interpreter
Classifier: License :: OSI Approved :: MIT License
Classifier: Programming Language :: Python :: 3
Requires-Python: >=3.8
Requires-Dist: typer>=0.6.1
